xoa_utils/__init__.py
xoa_utils/entry.py
xoa_utils/clicks/__init__.py
xoa_utils/clicks/click_backend.py
xoa_utils/clicks/click_help.py
xoa_utils/clicks/click_commands/__init__.py
xoa_utils/clicks/click_commands/an.py
xoa_utils/clicks/click_commands/anlt.py
xoa_utils/clicks/click_commands/debug.py
xoa_utils/clicks/click_commands/group.py
xoa_utils/clicks/click_commands/lt.py
xoa_utils/clicks/click_commands/management.py
xoa_utils/clicks/click_commands/models.py
xoa_utils/clis/__init__.py
xoa_utils/clis/cli_utils.py
xoa_utils/cmds/__init__.py
xoa_utils/cmds/cmd_context.py
xoa_utils/cmds/cmd_worker.py
xoa_utils/exceptions/__init__.py
xoa_utils/exceptions/exceptions.py
xoa_utils/hub/__init__.py
xoa_utils/hub/hub.py
xoa_utils/ssh_server/__init__.py
xoa_utils/ssh_server/xena_ssh_server.py
tdl_anlt_utility-1.0.0.dist-info/LICENSE
tdl_anlt_utility-1.0.0.dist-info/METADATA
tdl_anlt_utility-1.0.0.dist-info/WHEEL
tdl_anlt_utility-1.0.0.dist-info/entry_points.txt
tdl_anlt_utility-1.0.0.dist-info/top_level.txt
tdl_anlt_utility-1.0.0.dist-info/RECORD
